aliyunsdkvpc/__init__.py
aliyunsdkvpc/endpoint.py
aliyunsdkvpc/request/__init__.py
aliyunsdkvpc/request/v20160428/ActivateRouterInterfaceRequest.py
aliyunsdkvpc/request/v20160428/ActiveFlowLogRequest.py
aliyunsdkvpc/request/v20160428/AddBgpNetworkRequest.py
aliyunsdkvpc/request/v20160428/AddCommonBandwidthPackageIpRequest.py
aliyunsdkvpc/request/v20160428/AddCommonBandwidthPackageIpsRequest.py
aliyunsdkvpc/request/v20160428/AddGlobalAccelerationInstanceIpRequest.py
aliyunsdkvpc/request/v20160428/AddIPv6TranslatorAclListEntryRequest.py
aliyunsdkvpc/request/v20160428/AddPublicIpAddressPoolCidrBlockRequest.py
aliyunsdkvpc/request/v20160428/AddSourcesToTrafficMirrorSessionRequest.py
aliyunsdkvpc/request/v20160428/AllocateEipAddressProRequest.py
aliyunsdkvpc/request/v20160428/AllocateEipAddressRequest.py
aliyunsdkvpc/request/v20160428/AllocateEipSegmentAddressRequest.py
aliyunsdkvpc/request/v20160428/AllocateIpv6AddressRequest.py
aliyunsdkvpc/request/v20160428/AllocateIpv6InternetBandwidthRequest.py
aliyunsdkvpc/request/v20160428/AllocateVpcIpv6CidrRequest.py
aliyunsdkvpc/request/v20160428/ApplyPhysicalConnectionLOARequest.py
aliyunsdkvpc/request/v20160428/AssociateEipAddressBatchRequest.py
aliyunsdkvpc/request/v20160428/AssociateEipAddressRequest.py
aliyunsdkvpc/request/v20160428/AssociateHaVipRequest.py
aliyunsdkvpc/request/v20160428/AssociateNetworkAclRequest.py
aliyunsdkvpc/request/v20160428/AssociatePhysicalConnectionToVirtualBorderRouterRequest.py
aliyunsdkvpc/request/v20160428/AssociateRouteTableRequest.py
aliyunsdkvpc/request/v20160428/AssociateRouteTableWithGatewayRequest.py
aliyunsdkvpc/request/v20160428/AssociateRouteTablesWithVpcGatewayEndpointRequest.py
aliyunsdkvpc/request/v20160428/AssociateVpcCidrBlockRequest.py
aliyunsdkvpc/request/v20160428/AssociateVpnGatewayWithCertificateRequest.py
aliyunsdkvpc/request/v20160428/AttachDhcpOptionsSetToVpcRequest.py
aliyunsdkvpc/request/v20160428/AttachVbrToVpconnRequest.py
aliyun_python_sdk_vpc-3.0.47.dist-info/LICENSE
aliyun_python_sdk_vpc-3.0.47.dist-info/METADATA
aliyun_python_sdk_vpc-3.0.47.dist-info/WHEEL
aliyun_python_sdk_vpc-3.0.47.dist-info/top_level.txt
aliyun_python_sdk_vpc-3.0.47.dist-info/RECORD
